dcrux/__init__.py
dcrux/dcrux.py
dcrux-0.0.1.dist-info/LICENSE
dcrux-0.0.1.dist-info/METADATA
dcrux-0.0.1.dist-info/WHEEL
dcrux-0.0.1.dist-info/top_level.txt
dcrux-0.0.1.dist-info/RECORD
