Metadata-Version: 2.1
Name: dcrux
Version: 0.0.1
Summary: Dataset creation, management and analysis tool
Home-page: https://github.com/datasetcrux/dcrux
Author: Vinay Panchal
Author-email: vinay.npanchal@gmail.com
License: UNKNOWN
Project-URL: Bug Tracker, https://github.com/datasetcrux/dcrux/issues
Platform: UNKNOWN
Classifier: Programming Language :: Python :: 3
Classifier: License :: OSI Approved :: MIT License
Classifier: Operating System :: OS Independent
Requires-Python: >=3.6
License-File: LICENSE
